online_store/__init__.py
online_store/__main__.py
online_store/order_management.py
online_store/user_management.py
griperstore-0.1.0.dist-info/METADATA
griperstore-0.1.0.dist-info/WHEEL
griperstore-0.1.0.dist-info/top_level.txt
griperstore-0.1.0.dist-info/RECORD
